{"nodes": [{"id": "d_projects_faral_fararest_api_main_common_markers_ihavecustommapping_cs", "label": "IHaveCustomMapping.cs", "file_type": "code", "source_file": "D:\\Projects\\Faral\\fararest_api\\main\\Common\\Markers\\IHaveCustomMapping.cs", "source_location": "L1"}, {"id": "markers_ihavecustommapping_ihavecustommapping", "label": "IHaveCustomMapping", "file_type": "code", "source_file": "D:\\Projects\\Faral\\fararest_api\\main\\Common\\Markers\\IHaveCustomMapping.cs", "source_location": "L5"}, {"id": "markers_ihavecustommapping_ihavecustommapping_createmappings", "label": ".CreateMappings()", "file_type": "code", "source_file": "D:\\Projects\\Faral\\fararest_api\\main\\Common\\Markers\\IHaveCustomMapping.cs", "source_location": "L7"}], "edges": [{"source": "d_projects_faral_fararest_api_main_common_markers_ihavecustommapping_cs", "target": "automapper", "relation": "imports", "context": "import", "confidence": "EXTRACTED", "source_file": "D:\\Projects\\Faral\\fararest_api\\main\\Common\\Markers\\IHaveCustomMapping.cs", "source_location": "L1", "weight": 1.0}, {"source": "d_projects_faral_fararest_api_main_common_markers_ihavecustommapping_cs", "target": "markers_ihavecustommapping_ihavecustommapping", "relation": "contains", "confidence": "EXTRACTED", "source_file": "D:\\Projects\\Faral\\fararest_api\\main\\Common\\Markers\\IHaveCustomMapping.cs", "source_location": "L5", "weight": 1.0}, {"source": "markers_ihavecustommapping_ihavecustommapping", "target": "markers_ihavecustommapping_ihavecustommapping_createmappings", "relation": "method", "confidence": "EXTRACTED", "source_file": "D:\\Projects\\Faral\\fararest_api\\main\\Common\\Markers\\IHaveCustomMapping.cs", "source_location": "L7", "weight": 1.0}], "raw_calls": []}