{"nodes": [{"id": "d_projects_faral_fararest_api_main_services_contracts_agenttools_iagenttoolingservice_cs", "label": "IAgentToolingService.cs", "file_type": "code", "source_file": "D:\\Projects\\Faral\\fararest_api\\main\\Services\\Contracts\\AgentTools\\IAgentToolingService.cs", "source_location": "L1"}, {"id": "agenttools_iagenttoolingservice_iagenttoolingservice", "label": "IAgentToolingService", "file_type": "code", "source_file": "D:\\Projects\\Faral\\fararest_api\\main\\Services\\Contracts\\AgentTools\\IAgentToolingService.cs", "source_location": "L5"}, {"id": "agenttools_iagenttoolingservice_iagenttoolingservice_getcapabilitiesasync", "label": ".GetCapabilitiesAsync()", "file_type": "code", "source_file": "D:\\Projects\\Faral\\fararest_api\\main\\Services\\Contracts\\AgentTools\\IAgentToolingService.cs", "source_location": "L7"}, {"id": "agenttools_iagenttoolingservice_iagenttoolingservice_getdatabasestatusasync", "label": ".GetDatabaseStatusAsync()", "file_type": "code", "source_file": "D:\\Projects\\Faral\\fararest_api\\main\\Services\\Contracts\\AgentTools\\IAgentToolingService.cs", "source_location": "L8"}, {"id": "agenttools_iagenttoolingservice_iagenttoolingservice_getmemorystatusasync", "label": ".GetMemoryStatusAsync()", "file_type": "code", "source_file": "D:\\Projects\\Faral\\fararest_api\\main\\Services\\Contracts\\AgentTools\\IAgentToolingService.cs", "source_location": "L9"}], "edges": [{"source": "d_projects_faral_fararest_api_main_services_contracts_agenttools_iagenttoolingservice_cs", "target": "agenttools", "relation": "imports", "context": "import", "confidence": "EXTRACTED", "source_file": "D:\\Projects\\Faral\\fararest_api\\main\\Services\\Contracts\\AgentTools\\IAgentToolingService.cs", "source_location": "L1", "weight": 1.0}, {"source": "d_projects_faral_fararest_api_main_services_contracts_agenttools_iagenttoolingservice_cs", "target": "agenttools_iagenttoolingservice_iagenttoolingservice", "relation": "contains", "confidence": "EXTRACTED", "source_file": "D:\\Projects\\Faral\\fararest_api\\main\\Services\\Contracts\\AgentTools\\IAgentToolingService.cs", "source_location": "L5", "weight": 1.0}, {"source": "agenttools_iagenttoolingservice_iagenttoolingservice", "target": "agenttools_iagenttoolingservice_iagenttoolingservice_getcapabilitiesasync", "relation": "method", "confidence": "EXTRACTED", "source_file": "D:\\Projects\\Faral\\fararest_api\\main\\Services\\Contracts\\AgentTools\\IAgentToolingService.cs", "source_location": "L7", "weight": 1.0}, {"source": "agenttools_iagenttoolingservice_iagenttoolingservice", "target": "agenttools_iagenttoolingservice_iagenttoolingservice_getdatabasestatusasync", "relation": "method", "confidence": "EXTRACTED", "source_file": "D:\\Projects\\Faral\\fararest_api\\main\\Services\\Contracts\\AgentTools\\IAgentToolingService.cs", "source_location": "L8", "weight": 1.0}, {"source": "agenttools_iagenttoolingservice_iagenttoolingservice", "target": "agenttools_iagenttoolingservice_iagenttoolingservice_getmemorystatusasync", "relation": "method", "confidence": "EXTRACTED", "source_file": "D:\\Projects\\Faral\\fararest_api\\main\\Services\\Contracts\\AgentTools\\IAgentToolingService.cs", "source_location": "L9", "weight": 1.0}], "raw_calls": []}