{"nodes": [{"id": "d_projects_faral_fararest_api_main_services_dtos_mails_emailreceiverdto_cs", "label": "EmailReceiverDTO.cs", "file_type": "code", "source_file": "D:\\Projects\\Faral\\fararest_api\\main\\Services\\DTOs\\Mails\\EmailReceiverDTO.cs", "source_location": "L1"}, {"id": "mails_emailreceiverdto_emailreceiverdto", "label": "EmailReceiverDTO", "file_type": "code", "source_file": "D:\\Projects\\Faral\\fararest_api\\main\\Services\\DTOs\\Mails\\EmailReceiverDTO.cs", "source_location": "L8"}, {"id": "ihavecustommapping", "label": "IHaveCustomMapping", "file_type": "code", "source_file": "", "source_location": ""}, {"id": "mails_emailreceiverdto_emailreceiverdto_createmappings", "label": ".CreateMappings()", "file_type": "code", "source_file": "D:\\Projects\\Faral\\fararest_api\\main\\Services\\DTOs\\Mails\\EmailReceiverDTO.cs", "source_location": "L15"}], "edges": [{"source": "d_projects_faral_fararest_api_main_services_dtos_mails_emailreceiverdto_cs", "target": "markers", "relation": "imports", "context": "import", "confidence": "EXTRACTED", "source_file": "D:\\Projects\\Faral\\fararest_api\\main\\Services\\DTOs\\Mails\\EmailReceiverDTO.cs", "source_location": "L1", "weight": 1.0}, {"source": "d_projects_faral_fararest_api_main_services_dtos_mails_emailreceiverdto_cs", "target": "extensions", "relation": "imports", "context": "import", "confidence": "EXTRACTED", "source_file": "D:\\Projects\\Faral\\fararest_api\\main\\Services\\DTOs\\Mails\\EmailReceiverDTO.cs", "source_location": "L2", "weight": 1.0}, {"source": "d_projects_faral_fararest_api_main_services_dtos_mails_emailreceiverdto_cs", "target": "emails", "relation": "imports", "context": "import", "confidence": "EXTRACTED", "source_file": "D:\\Projects\\Faral\\fararest_api\\main\\Services\\DTOs\\Mails\\EmailReceiverDTO.cs", "source_location": "L3", "weight": 1.0}, {"source": "d_projects_faral_fararest_api_main_services_dtos_mails_emailreceiverdto_cs", "target": "emails", "relation": "imports", "context": "import", "confidence": "EXTRACTED", "source_file": "D:\\Projects\\Faral\\fararest_api\\main\\Services\\DTOs\\Mails\\EmailReceiverDTO.cs", "source_location": "L4", "weight": 1.0}, {"source": "d_projects_faral_fararest_api_main_services_dtos_mails_emailreceiverdto_cs", "target": "mails_emailreceiverdto_emailreceiverdto", "relation": "contains", "confidence": "EXTRACTED", "source_file": "D:\\Projects\\Faral\\fararest_api\\main\\Services\\DTOs\\Mails\\EmailReceiverDTO.cs", "source_location": "L8", "weight": 1.0}, {"source": "mails_emailreceiverdto_emailreceiverdto", "target": "ihavecustommapping", "relation": "inherits", "confidence": "EXTRACTED", "source_file": "D:\\Projects\\Faral\\fararest_api\\main\\Services\\DTOs\\Mails\\EmailReceiverDTO.cs", "source_location": "L8", "weight": 1.0}, {"source": "mails_emailreceiverdto_emailreceiverdto", "target": "mails_emailreceiverdto_emailreceiverdto_createmappings", "relation": "method", "confidence": "EXTRACTED", "source_file": "D:\\Projects\\Faral\\fararest_api\\main\\Services\\DTOs\\Mails\\EmailReceiverDTO.cs", "source_location": "L15", "weight": 1.0}], "raw_calls": [{"caller_nid": "mails_emailreceiverdto_emailreceiverdto_createmappings", "callee": "CreateMap<Email, EmailReceiverDTO>", "is_member_call": true, "source_file": "D:\\Projects\\Faral\\fararest_api\\main\\Services\\DTOs\\Mails\\EmailReceiverDTO.cs", "source_location": "L17"}]}