{"nodes": [{"id": "d_projects_faral_fararest_api_main_services_dtos_common_pagingdto_cs", "label": "PagingDTO.cs", "file_type": "code", "source_file": "D:\\Projects\\Faral\\fararest_api\\main\\Services\\DTOs\\Common\\PagingDTO.cs", "source_location": "L1"}, {"id": "common_pagingdto_pagingdto", "label": "PagingDTO", "file_type": "code", "source_file": "D:\\Projects\\Faral\\fararest_api\\main\\Services\\DTOs\\Common\\PagingDTO.cs", "source_location": "L3"}, {"id": "pagingwithoutdata", "label": "PagingWithoutData", "file_type": "code", "source_file": "", "source_location": ""}, {"id": "common_pagingdto_pagingwithoutdata", "label": "PagingWithoutData", "file_type": "code", "source_file": "D:\\Projects\\Faral\\fararest_api\\main\\Services\\DTOs\\Common\\PagingDTO.cs", "source_location": "L19"}], "edges": [{"source": "d_projects_faral_fararest_api_main_services_dtos_common_pagingdto_cs", "target": "common_pagingdto_pagingdto", "relation": "contains", "confidence": "EXTRACTED", "source_file": "D:\\Projects\\Faral\\fararest_api\\main\\Services\\DTOs\\Common\\PagingDTO.cs", "source_location": "L3", "weight": 1.0}, {"source": "common_pagingdto_pagingdto", "target": "pagingwithoutdata", "relation": "inherits", "confidence": "EXTRACTED", "source_file": "D:\\Projects\\Faral\\fararest_api\\main\\Services\\DTOs\\Common\\PagingDTO.cs", "source_location": "L3", "weight": 1.0}, {"source": "d_projects_faral_fararest_api_main_services_dtos_common_pagingdto_cs", "target": "common_pagingdto_pagingwithoutdata", "relation": "contains", "confidence": "EXTRACTED", "source_file": "D:\\Projects\\Faral\\fararest_api\\main\\Services\\DTOs\\Common\\PagingDTO.cs", "source_location": "L19", "weight": 1.0}], "raw_calls": []}