{"nodes": [{"id": "d_projects_faral_fararest_api_main_common_utilities_helpers_assert_cs", "label": "Assert.cs", "file_type": "code", "source_file": "D:\\Projects\\Faral\\fararest_api\\main\\Common\\Utilities\\Helpers\\Assert.cs", "source_location": "L1"}, {"id": "helpers_assert_assert", "label": "Assert", "file_type": "code", "source_file": "D:\\Projects\\Faral\\fararest_api\\main\\Common\\Utilities\\Helpers\\Assert.cs", "source_location": "L7"}, {"id": "helpers_assert_assert_notnull", "label": ".NotNull()", "file_type": "code", "source_file": "D:\\Projects\\Faral\\fararest_api\\main\\Common\\Utilities\\Helpers\\Assert.cs", "source_location": "L9"}, {"id": "helpers_assert_assert_notempty", "label": ".NotEmpty()", "file_type": "code", "source_file": "D:\\Projects\\Faral\\fararest_api\\main\\Common\\Utilities\\Helpers\\Assert.cs", "source_location": "L24"}, {"id": "helpers_assert_regularexpression", "label": "RegularExpression", "file_type": "code", "source_file": "D:\\Projects\\Faral\\fararest_api\\main\\Common\\Utilities\\Helpers\\Assert.cs", "source_location": "L36"}, {"id": "string", "label": "string", "file_type": "code", "source_file": "D:\\Projects\\Faral\\fararest_api\\main\\Common\\Utilities\\Helpers\\Assert.cs", "source_location": "L39"}, {"id": "helpers_assert_codegenerator", "label": "CodeGenerator", "file_type": "code", "source_file": "D:\\Projects\\Faral\\fararest_api\\main\\Common\\Utilities\\Helpers\\Assert.cs", "source_location": "L53"}, {"id": "random", "label": "Random", "file_type": "code", "source_file": "D:\\Projects\\Faral\\fararest_api\\main\\Common\\Utilities\\Helpers\\Assert.cs", "source_location": "L55"}, {"id": "helpers_assert_codegenerator_generaterandomnumber", "label": ".GenerateRandomNumber()", "file_type": "code", "source_file": "D:\\Projects\\Faral\\fararest_api\\main\\Common\\Utilities\\Helpers\\Assert.cs", "source_location": "L59"}, {"id": "helpers_assert_codegenerator_generaterandomstring", "label": ".GenerateRandomString()", "file_type": "code", "source_file": "D:\\Projects\\Faral\\fararest_api\\main\\Common\\Utilities\\Helpers\\Assert.cs", "source_location": "L67"}, {"id": "helpers_assert_codegenerator_createcodeverifier", "label": ".CreateCodeVerifier()", "file_type": "code", "source_file": "D:\\Projects\\Faral\\fararest_api\\main\\Common\\Utilities\\Helpers\\Assert.cs", "source_location": "L75"}, {"id": "helpers_assert_codegenerator_generatecodechallenge", "label": ".GenerateCodeChallenge()", "file_type": "code", "source_file": "D:\\Projects\\Faral\\fararest_api\\main\\Common\\Utilities\\Helpers\\Assert.cs", "source_location": "L85"}], "edges": [{"source": "d_projects_faral_fararest_api_main_common_utilities_helpers_assert_cs", "target": "collections", "relation": "imports", "context": "import", "confidence": "EXTRACTED", "source_file": "D:\\Projects\\Faral\\fararest_api\\main\\Common\\Utilities\\Helpers\\Assert.cs", "source_location": "L1", "weight": 1.0}, {"source": "d_projects_faral_fararest_api_main_common_utilities_helpers_assert_cs", "target": "cryptography", "relation": "imports", "context": "import", "confidence": "EXTRACTED", "source_file": "D:\\Projects\\Faral\\fararest_api\\main\\Common\\Utilities\\Helpers\\Assert.cs", "source_location": "L2", "weight": 1.0}, {"source": "d_projects_faral_fararest_api_main_common_utilities_helpers_assert_cs", "target": "text", "relation": "imports", "context": "import", "confidence": "EXTRACTED", "source_file": "D:\\Projects\\Faral\\fararest_api\\main\\Common\\Utilities\\Helpers\\Assert.cs", "source_location": "L3", "weight": 1.0}, {"source": "d_projects_faral_fararest_api_main_common_utilities_helpers_assert_cs", "target": "helpers_assert_assert", "relation": "contains", "confidence": "EXTRACTED", "source_file": "D:\\Projects\\Faral\\fararest_api\\main\\Common\\Utilities\\Helpers\\Assert.cs", "source_location": "L7", "weight": 1.0}, {"source": "helpers_assert_assert", "target": "helpers_assert_assert_notnull", "relation": "method", "confidence": "EXTRACTED", "source_file": "D:\\Projects\\Faral\\fararest_api\\main\\Common\\Utilities\\Helpers\\Assert.cs", "source_location": "L9", "weight": 1.0}, {"source": "helpers_assert_assert", "target": "helpers_assert_assert_notnull", "relation": "method", "confidence": "EXTRACTED", "source_file": "D:\\Projects\\Faral\\fararest_api\\main\\Common\\Utilities\\Helpers\\Assert.cs", "source_location": "L16", "weight": 1.0}, {"source": "helpers_assert_assert", "target": "helpers_assert_assert_notempty", "relation": "method", "confidence": "EXTRACTED", "source_file": "D:\\Projects\\Faral\\fararest_api\\main\\Common\\Utilities\\Helpers\\Assert.cs", "source_location": "L24", "weight": 1.0}, {"source": "d_projects_faral_fararest_api_main_common_utilities_helpers_assert_cs", "target": "helpers_assert_regularexpression", "relation": "contains", "confidence": "EXTRACTED", "source_file": "D:\\Projects\\Faral\\fararest_api\\main\\Common\\Utilities\\Helpers\\Assert.cs", "source_location": "L36", "weight": 1.0}, {"source": "helpers_assert_regularexpression", "target": "string", "relation": "references", "confidence": "EXTRACTED", "source_file": "D:\\Projects\\Faral\\fararest_api\\main\\Common\\Utilities\\Helpers\\Assert.cs", "source_location": "L39", "weight": 1.0, "context": "field"}, {"source": "helpers_assert_regularexpression", "target": "string", "relation": "references", "confidence": "EXTRACTED", "source_file": "D:\\Projects\\Faral\\fararest_api\\main\\Common\\Utilities\\Helpers\\Assert.cs", "source_location": "L40", "weight": 1.0, "context": "field"}, {"source": "helpers_assert_regularexpression", "target": "string", "relation": "references", "confidence": "EXTRACTED", "source_file": "D:\\Projects\\Faral\\fararest_api\\main\\Common\\Utilities\\Helpers\\Assert.cs", "source_location": "L41", "weight": 1.0, "context": "field"}, {"source": "helpers_assert_regularexpression", "target": "string", "relation": "references", "confidence": "EXTRACTED", "source_file": "D:\\Projects\\Faral\\fararest_api\\main\\Common\\Utilities\\Helpers\\Assert.cs", "source_location": "L42", "weight": 1.0, "context": "field"}, {"source": "helpers_assert_regularexpression", "target": "string", "relation": "references", "confidence": "EXTRACTED", "source_file": "D:\\Projects\\Faral\\fararest_api\\main\\Common\\Utilities\\Helpers\\Assert.cs", "source_location": "L43", "weight": 1.0, "context": "field"}, {"source": "helpers_assert_regularexpression", "target": "string", "relation": "references", "confidence": "EXTRACTED", "source_file": "D:\\Projects\\Faral\\fararest_api\\main\\Common\\Utilities\\Helpers\\Assert.cs", "source_location": "L44", "weight": 1.0, "context": "field"}, {"source": "helpers_assert_regularexpression", "target": "string", "relation": "references", "confidence": "EXTRACTED", "source_file": "D:\\Projects\\Faral\\fararest_api\\main\\Common\\Utilities\\Helpers\\Assert.cs", "source_location": "L45", "weight": 1.0, "context": "field"}, {"source": "helpers_assert_regularexpression", "target": "string", "relation": "references", "confidence": "EXTRACTED", "source_file": "D:\\Projects\\Faral\\fararest_api\\main\\Common\\Utilities\\Helpers\\Assert.cs", "source_location": "L46", "weight": 1.0, "context": "field"}, {"source": "helpers_assert_regularexpression", "target": "string", "relation": "references", "confidence": "EXTRACTED", "source_file": "D:\\Projects\\Faral\\fararest_api\\main\\Common\\Utilities\\Helpers\\Assert.cs", "source_location": "L47", "weight": 1.0, "context": "field"}, {"source": "helpers_assert_regularexpression", "target": "string", "relation": "references", "confidence": "EXTRACTED", "source_file": "D:\\Projects\\Faral\\fararest_api\\main\\Common\\Utilities\\Helpers\\Assert.cs", "source_location": "L48", "weight": 1.0, "context": "field"}, {"source": "helpers_assert_regularexpression", "target": "string", "relation": "references", "confidence": "EXTRACTED", "source_file": "D:\\Projects\\Faral\\fararest_api\\main\\Common\\Utilities\\Helpers\\Assert.cs", "source_location": "L49", "weight": 1.0, "context": "field"}, {"source": "d_projects_faral_fararest_api_main_common_utilities_helpers_assert_cs", "target": "helpers_assert_codegenerator", "relation": "contains", "confidence": "EXTRACTED", "source_file": "D:\\Projects\\Faral\\fararest_api\\main\\Common\\Utilities\\Helpers\\Assert.cs", "source_location": "L53", "weight": 1.0}, {"source": "helpers_assert_codegenerator", "target": "random", "relation": "references", "confidence": "EXTRACTED", "source_file": "D:\\Projects\\Faral\\fararest_api\\main\\Common\\Utilities\\Helpers\\Assert.cs", "source_location": "L55", "weight": 1.0, "context": "field"}, {"source": "helpers_assert_codegenerator", "target": "helpers_assert_codegenerator_generaterandomnumber", "relation": "method", "confidence": "EXTRACTED", "source_file": "D:\\Projects\\Faral\\fararest_api\\main\\Common\\Utilities\\Helpers\\Assert.cs", "source_location": "L59", "weight": 1.0}, {"source": "helpers_assert_codegenerator", "target": "helpers_assert_codegenerator_generaterandomstring", "relation": "method", "confidence": "EXTRACTED", "source_file": "D:\\Projects\\Faral\\fararest_api\\main\\Common\\Utilities\\Helpers\\Assert.cs", "source_location": "L67", "weight": 1.0}, {"source": "helpers_assert_codegenerator", "target": "helpers_assert_codegenerator_createcodeverifier", "relation": "method", "confidence": "EXTRACTED", "source_file": "D:\\Projects\\Faral\\fararest_api\\main\\Common\\Utilities\\Helpers\\Assert.cs", "source_location": "L75", "weight": 1.0}, {"source": "helpers_assert_codegenerator", "target": "helpers_assert_codegenerator_generatecodechallenge", "relation": "method", "confidence": "EXTRACTED", "source_file": "D:\\Projects\\Faral\\fararest_api\\main\\Common\\Utilities\\Helpers\\Assert.cs", "source_location": "L85", "weight": 1.0}], "raw_calls": [{"caller_nid": "helpers_assert_assert_notempty", "callee": "IsNullOrWhiteSpace", "is_member_call": true, "source_file": "D:\\Projects\\Faral\\fararest_api\\main\\Common\\Utilities\\Helpers\\Assert.cs", "source_location": "L28"}, {"caller_nid": "helpers_assert_assert_notempty", "callee": "Any", "is_member_call": true, "source_file": "D:\\Projects\\Faral\\fararest_api\\main\\Common\\Utilities\\Helpers\\Assert.cs", "source_location": "L29"}, {"caller_nid": "helpers_assert_assert_notempty", "callee": "Cast<object>", "is_member_call": true, "source_file": "D:\\Projects\\Faral\\fararest_api\\main\\Common\\Utilities\\Helpers\\Assert.cs", "source_location": "L29"}, {"caller_nid": "helpers_assert_codegenerator_generaterandomnumber", "callee": "ToArray", "is_member_call": true, "source_file": "D:\\Projects\\Faral\\fararest_api\\main\\Common\\Utilities\\Helpers\\Assert.cs", "source_location": "L63"}, {"caller_nid": "helpers_assert_codegenerator_generaterandomnumber", "callee": "Select", "is_member_call": true, "source_file": "D:\\Projects\\Faral\\fararest_api\\main\\Common\\Utilities\\Helpers\\Assert.cs", "source_location": "L63"}, {"caller_nid": "helpers_assert_codegenerator_generaterandomnumber", "callee": "Repeat", "is_member_call": true, "source_file": "D:\\Projects\\Faral\\fararest_api\\main\\Common\\Utilities\\Helpers\\Assert.cs", "source_location": "L63"}, {"caller_nid": "helpers_assert_codegenerator_generaterandomnumber", "callee": "Next", "is_member_call": true, "source_file": "D:\\Projects\\Faral\\fararest_api\\main\\Common\\Utilities\\Helpers\\Assert.cs", "source_location": "L64"}, {"caller_nid": "helpers_assert_codegenerator_generaterandomstring", "callee": "ToArray", "is_member_call": true, "source_file": "D:\\Projects\\Faral\\fararest_api\\main\\Common\\Utilities\\Helpers\\Assert.cs", "source_location": "L71"}, {"caller_nid": "helpers_assert_codegenerator_generaterandomstring", "callee": "Select", "is_member_call": true, "source_file": "D:\\Projects\\Faral\\fararest_api\\main\\Common\\Utilities\\Helpers\\Assert.cs", "source_location": "L71"}, {"caller_nid": "helpers_assert_codegenerator_generaterandomstring", "callee": "Repeat", "is_member_call": true, "source_file": "D:\\Projects\\Faral\\fararest_api\\main\\Common\\Utilities\\Helpers\\Assert.cs", "source_location": "L71"}, {"caller_nid": "helpers_assert_codegenerator_generaterandomstring", "callee": "Next", "is_member_call": true, "source_file": "D:\\Projects\\Faral\\fararest_api\\main\\Common\\Utilities\\Helpers\\Assert.cs", "source_location": "L72"}, {"caller_nid": "helpers_assert_codegenerator_createcodeverifier", "callee": "Next", "is_member_call": true, "source_file": "D:\\Projects\\Faral\\fararest_api\\main\\Common\\Utilities\\Helpers\\Assert.cs", "source_location": "L80"}, {"caller_nid": "helpers_assert_codegenerator_createcodeverifier", "callee": "Replace", "is_member_call": true, "source_file": "D:\\Projects\\Faral\\fararest_api\\main\\Common\\Utilities\\Helpers\\Assert.cs", "source_location": "L82"}, {"caller_nid": "helpers_assert_codegenerator_createcodeverifier", "callee": "Replace", "is_member_call": true, "source_file": "D:\\Projects\\Faral\\fararest_api\\main\\Common\\Utilities\\Helpers\\Assert.cs", "source_location": "L82"}, {"caller_nid": "helpers_assert_codegenerator_createcodeverifier", "callee": "Replace", "is_member_call": true, "source_file": "D:\\Projects\\Faral\\fararest_api\\main\\Common\\Utilities\\Helpers\\Assert.cs", "source_location": "L82"}, {"caller_nid": "helpers_assert_codegenerator_createcodeverifier", "callee": "ToBase64String", "is_member_call": true, "source_file": "D:\\Projects\\Faral\\fararest_api\\main\\Common\\Utilities\\Helpers\\Assert.cs", "source_location": "L82"}, {"caller_nid": "helpers_assert_codegenerator_createcodeverifier", "callee": "GetBytes", "is_member_call": true, "source_file": "D:\\Projects\\Faral\\fararest_api\\main\\Common\\Utilities\\Helpers\\Assert.cs", "source_location": "L82"}, {"caller_nid": "helpers_assert_codegenerator_generatecodechallenge", "callee": "Create", "is_member_call": true, "source_file": "D:\\Projects\\Faral\\fararest_api\\main\\Common\\Utilities\\Helpers\\Assert.cs", "source_location": "L87"}, {"caller_nid": "helpers_assert_codegenerator_generatecodechallenge", "callee": "ComputeHash", "is_member_call": true, "source_file": "D:\\Projects\\Faral\\fararest_api\\main\\Common\\Utilities\\Helpers\\Assert.cs", "source_location": "L88"}, {"caller_nid": "helpers_assert_codegenerator_generatecodechallenge", "callee": "GetBytes", "is_member_call": true, "source_file": "D:\\Projects\\Faral\\fararest_api\\main\\Common\\Utilities\\Helpers\\Assert.cs", "source_location": "L88"}, {"caller_nid": "helpers_assert_codegenerator_generatecodechallenge", "callee": "Replace", "is_member_call": true, "source_file": "D:\\Projects\\Faral\\fararest_api\\main\\Common\\Utilities\\Helpers\\Assert.cs", "source_location": "L89"}, {"caller_nid": "helpers_assert_codegenerator_generatecodechallenge", "callee": "Replace", "is_member_call": true, "source_file": "D:\\Projects\\Faral\\fararest_api\\main\\Common\\Utilities\\Helpers\\Assert.cs", "source_location": "L89"}, {"caller_nid": "helpers_assert_codegenerator_generatecodechallenge", "callee": "Replace", "is_member_call": true, "source_file": "D:\\Projects\\Faral\\fararest_api\\main\\Common\\Utilities\\Helpers\\Assert.cs", "source_location": "L89"}, {"caller_nid": "helpers_assert_codegenerator_generatecodechallenge", "callee": "ToBase64String", "is_member_call": true, "source_file": "D:\\Projects\\Faral\\fararest_api\\main\\Common\\Utilities\\Helpers\\Assert.cs", "source_location": "L89"}]}